pysomit/__init__.py
pysomit-0.1.0.dist-info/licenses/LICENSE
pysomit-0.1.0.dist-info/METADATA
pysomit-0.1.0.dist-info/WHEEL
pysomit-0.1.0.dist-info/top_level.txt
pysomit-0.1.0.dist-info/RECORD
