Metadata-Version: 2.4
Name: pysomit
Version: 0.1.0
Summary: SOMIT library
Home-page: https://github.com/Dr-WangZhiyuan/pysomit
Author: Dr. Zhiyuan Wang
Author-email: wang1399@e.ntu.edu.sg
License: MIT
Classifier: Programming Language :: Python :: 3
Classifier: License :: OSI Approved :: MIT License
License-File: LICENSE
Dynamic: author
Dynamic: author-email
Dynamic: classifier
Dynamic: description
Dynamic: description-content-type
Dynamic: home-page
Dynamic: license
Dynamic: license-file
Dynamic: summary
